secondproject/__init__.py
secondproject/polynom.py
secondproject/polynom_test.py
secondproject-0.0.1.dist-info/METADATA
secondproject-0.0.1.dist-info/WHEEL
secondproject-0.0.1.dist-info/top_level.txt
secondproject-0.0.1.dist-info/RECORD
