Metadata-Version: 2.1
Name: secondproject
Version: 0.0.1
Summary: my first PypI package
Home-page: UNKNOWN
Author: Antoine Marullaz
Author-email: antoine.marullaz@gmail.com
License: UNKNOWN
Keywords: example documentation tutorial
Platform: UNKNOWN
